[
	{
		"time": 1738240622324,
		"file": "2025-01-30-15-37-02.zip",
		"index": 275,
		"success": true,
		"size": 14464047
	},
	{
		"time": 1738247822201,
		"file": "2025-01-30-17-37-02.zip",
		"index": 276,
		"success": true,
		"size": 14751055
	},
	{
		"time": 1738402755381,
		"file": "2025-02-01-12-39-15.zip",
		"index": 277,
		"success": true,
		"size": 14750473
	},
	{
		"time": 1738409955316,
		"file": "2025-02-01-14-39-15.zip",
		"index": 278,
		"success": true,
		"size": 14751796
	},
	{
		"time": 1738417155350,
		"file": "2025-02-01-16-39-15.zip",
		"index": 279,
		"success": true,
		"size": 14754805
	},
	{
		"time": 1738513998269,
		"file": "2025-02-02-19-33-18.zip",
		"index": 280,
		"success": true,
		"size": 14755248
	},
	{
		"time": 1738565730977,
		"file": "2025-02-03-09-55-30.zip",
		"index": 281,
		"success": true,
		"size": 14752448
	},
	{
		"time": 1738671190115,
		"file": "2025-02-04-15-13-10.zip",
		"index": 282,
		"success": true,
		"size": 14753868
	},
	{
		"time": 1738752185989,
		"file": "2025-02-05-13-43-05.zip",
		"index": 283,
		"success": true,
		"size": 14760959
	},
	{
		"time": 1738767370102,
		"file": "2025-02-05-17-56-10.zip",
		"index": 284,
		"success": true,
		"size": 14763682
	},
	{
		"time": 1738855445525,
		"file": "2025-02-06-18-24-05.zip",
		"index": 285,
		"success": true,
		"size": 14764922
	},
	{
		"time": 1738862645602,
		"file": "2025-02-06-20-24-05.zip",
		"index": 286,
		"success": true,
		"size": 14755209
	}
]